{"_links": {"self": {"href": "https://eu.api.blizzard.com/data/wow/mount/408?namespace=static-12.0.0_65028-eu"}}, "id": 408, "name": "Mottled Drake", "creature_displays": [{"key": {"href": "https://eu.api.blizzard.com/data/wow/media/creature-display/37231?namespace=static-12.0.0_65028-eu"}, "id": 37231}], "description": "I thought the thing was ill until it took to the air. It flies as true as any of my own. -Alexstrasza", "source": {"type": "TCG", "name": "Trading Card Game"}, "should_exclude_if_uncollected": true}