{"_links": {"self": {"href": "https://eu.api.blizzard.com/data/wow/mount/2620?namespace=static-12.0.0_65028-eu"}}, "id": 2620, "name": "Void-Razed Elekk", "creature_displays": [{"key": {"href": "https://eu.api.blizzard.com/data/wow/media/creature-display/131304?namespace=static-12.0.0_65028-eu"}, "id": 131304}], "description": "Their temperament is as wild as the twisted forces that warped their creation and they only serve who they choose.", "source": {"type": "TRADINGPOST", "name": "Trading Post"}, "should_exclude_if_uncollected": true}