{"_links": {"self": {"href": "https://eu.api.blizzard.com/data/wow/mount/257?namespace=static-12.0.0_65028-eu"}}, "id": 257, "name": "Wooly Mammoth", "creature_displays": [{"key": {"href": "https://eu.api.blizzard.com/data/wow/media/creature-display/27244?namespace=static-12.0.0_65028-eu"}, "id": 27244}], "description": "This wild variant of the mammoth is not bred for riding. Most wooly mammoths are captured in the wild and tamed by their riders, resulting in a fierce, cunning mount.", "source": {"type": "VENDOR", "name": "Vendor"}, "faction": {"type": "HORDE", "name": "Horde"}, "requirements": {"faction": {"type": "HORDE", "name": "Horde"}}}