{"_links": {"self": {"href": "https://eu.api.blizzard.com/data/wow/mount/2660?namespace=static-12.0.0_65028-eu"}}, "id": 2660, "name": "Leystone Basilisk", "creature_displays": [{"key": {"href": "https://eu.api.blizzard.com/data/wow/media/creature-display/136186?namespace=static-12.0.0_65028-eu"}, "id": 136186}], "description": "This beautiful basilisk is often hunted for the magical properties of its organs. Fortunately for the basilisk, its connection to ley lines gives it a prescient sense of approaching predators.", "source": {"type": "WORLDEVENT", "name": "World Event"}, "should_exclude_if_uncollected": true}