{"_links": {"self": {"href": "https://eu.api.blizzard.com/data/wow/mount/986?namespace=static-12.0.0_65028-eu"}}, "id": 986, "name": "Bleakhoof Ruinstrider", "creature_displays": [{"key": {"href": "https://eu.api.blizzard.com/data/wow/media/creature-display/79440?namespace=static-12.0.0_65028-eu"}, "id": 79440}], "description": "The Army of the Light could only save so many of Argus' native species; countless numbers were lost to chaos.", "source": {"type": "ACHIEVEMENT", "name": "Achievement"}}