{"_links": {"self": {"href": "https://eu.api.blizzard.com/data/wow/mount/1410?namespace=static-12.0.0_65028-eu"}}, "id": 1410, "name": "Hulking Deathroc", "creature_displays": [{"key": {"href": "https://eu.api.blizzard.com/data/wow/media/creature-display/98149?namespace=static-12.0.0_65028-eu"}, "id": 98149}], "description": "Deathrocs are stitched monstrosities from the discarded viscera, bone, and organs that were not required to construct soldiers for the House of Constructs.", "source": {"type": "DROP", "name": "Drop"}}