{"_links": {"self": {"href": "https://eu.api.blizzard.com/data/wow/mount/2090?namespace=static-12.0.0_65028-eu"}}, "id": 2090, "name": "Polly Roger", "creature_displays": [{"key": {"href": "https://eu.api.blizzard.com/data/wow/media/creature-display/117262?namespace=static-12.0.0_65028-eu"}, "id": 117262}], "description": "The scourge of the slightly-northeastern seas, giant parrots like Polly can live for up to 2000 years. What a wonderful curse on your next of kin.", "source": {"type": "DROP", "name": "Drop"}, "should_exclude_if_uncollected": true}