{"_links": {"self": {"href": "https://eu.api.blizzard.com/data/wow/mount/1359?namespace=static-12.0.0_65028-eu"}}, "id": 1359, "name": "Enchanted Winterborn Runestag", "creature_displays": [{"key": {"href": "https://eu.api.blizzard.com/data/wow/media/creature-display/94365?namespace=static-12.0.0_65028-eu"}, "id": 94365}], "description": "Winterborn runestags are the favored mount of the Winter Queen herself, and she only bestows such a creature on her most favored subjects.", "source": {"type": "DROP", "name": "Drop"}}