{"_links": {"self": {"href": "https://eu.api.blizzard.com/data/wow/mount/469?namespace=static-12.0.0_65028-eu"}}, "id": 469, "name": "Depleted-Kyparium Rocket", "creature_displays": [{"key": {"href": "https://eu.api.blizzard.com/data/wow/media/creature-display/43637?namespace=static-12.0.0_65028-eu"}, "id": 43637}], "description": "When Kyparite is depleted of its amber essence it becomes fairly resistant to the corrosion from rocket fuel.", "source": {"type": "PROFESSION", "name": "Profession"}}