{"_links": {"self": {"href": "https://eu.api.blizzard.com/data/wow/mount/64?namespace=static-12.0.0_65028-eu"}}, "id": 64, "name": "Black Ram", "creature_displays": [{"key": {"href": "https://eu.api.blizzard.com/data/wow/media/creature-display/2784?namespace=static-12.0.0_65028-eu"}, "id": 2784}], "description": "I've not seen this breed in in ages, but when they're ram tough they stick around. -Veron Amberstill", "source": {"type": "VENDOR", "name": "Vendor"}, "faction": {"type": "ALLIANCE", "name": "Alliance"}, "should_exclude_if_uncollected": true, "requirements": {"faction": {"type": "ALLIANCE", "name": "Alliance"}}}