{"_links": {"self": {"href": "https://eu.api.blizzard.com/data/wow/mount/157?namespace=static-12.0.0_65028-eu"}}, "id": 157, "name": "Purple Hawkstrider", "creature_displays": [{"key": {"href": "https://eu.api.blizzard.com/data/wow/media/creature-display/19479?namespace=static-12.0.0_65028-eu"}, "id": 19479}], "description": "Some of our brethren prefer horses, but the hawkstrider will always be the true symbol of Silvermoon. -Winaestra", "source": {"type": "VENDOR", "name": "Vendor"}, "faction": {"type": "HORDE", "name": "Horde"}, "requirements": {"faction": {"type": "HORDE", "name": "Horde"}}}