{"_links": {"self": {"href": "https://eu.api.blizzard.com/data/wow/mount/2342?namespace=static-12.0.0_65028-eu"}}, "id": 2342, "name": "Meeksi Rufflefur", "creature_displays": [{"key": {"href": "https://eu.api.blizzard.com/data/wow/media/creature-display/124509?namespace=static-12.0.0_65028-eu"}, "id": 124509}], "description": "Rufflefurs are playful, clumsy and obsessed with cleanliness. This is a dangerous combination of traits.", "source": {"type": "PETSTORE", "name": "In-Game Shop"}, "should_exclude_if_uncollected": true}